odoo/addons/product_fao_fishing/README.rst
odoo/addons/product_fao_fishing/__init__.py
odoo/addons/product_fao_fishing/__manifest__.py
odoo/addons/product_fao_fishing/data/product_fao_fishing_data.xml
odoo/addons/product_fao_fishing/data/product_fao_fishing_technique_data.xml
odoo/addons/product_fao_fishing/i18n/es.po
odoo/addons/product_fao_fishing/i18n/it.po
odoo/addons/product_fao_fishing/i18n/product_fao_fishing.pot
odoo/addons/product_fao_fishing/i18n/pt_BR.po
odoo/addons/product_fao_fishing/models/__init__.py
odoo/addons/product_fao_fishing/models/product_attribute.py
odoo/addons/product_fao_fishing/models/product_template.py
odoo/addons/product_fao_fishing/readme/CONFIGURE.md
odoo/addons/product_fao_fishing/readme/CONTRIBUTORS.md
odoo/addons/product_fao_fishing/readme/DESCRIPTION.md
odoo/addons/product_fao_fishing/readme/USAGE.md
odoo/addons/product_fao_fishing/static/description/icon.png
odoo/addons/product_fao_fishing/static/description/index.html
odoo/addons/product_fao_fishing/tests/__init__.py
odoo/addons/product_fao_fishing/tests/test_product_fao_fishing.py
odoo/addons/product_fao_fishing/views/product_attribute_views.xml
odoo_addon_product_fao_fishing-18.0.1.0.0.2.dist-info/METADATA
odoo_addon_product_fao_fishing-18.0.1.0.0.2.dist-info/WHEEL
odoo_addon_product_fao_fishing-18.0.1.0.0.2.dist-info/top_level.txt
odoo_addon_product_fao_fishing-18.0.1.0.0.2.dist-info/RECORD
