Metadata-Version: 2.1
Name: odoo-addon-product_fao_fishing
Version: 18.0.1.0.0.2
Requires-Python: >=3.10
Requires-Dist: odoo-addon-product_attribute_value_avoid_auto_fill==18.0.*
Requires-Dist: odoo==18.0.*
Summary: Set fishing areas and capture technology
Home-page: https://github.com/OCA/community-data-files
License: AGPL-3
Author: Tecnativa, Odoo Community Association (OCA)
Author-email: support@odoo-community.org
Classifier: Programming Language :: Python
Classifier: Framework :: Odoo
Classifier: Framework :: Odoo :: 18.0
Classifier: License :: OSI Approved :: GNU Affero General Public License v3
Classifier: Development Status :: 4 - Beta
